forwagent/agent.py
forwagent/cli.py
forwagent/common.py
forwagent/config.py
forwagent/server.py
forwagent-0.1.0.dist-info/entry_points.txt
forwagent-0.1.0.dist-info/LICENSE
forwagent-0.1.0.dist-info/WHEEL
forwagent-0.1.0.dist-info/METADATA
forwagent-0.1.0.dist-info/RECORD
